qen/__init__.py
qen/cli.py
qen/config.py
qen/git_utils.py
qen/init_utils.py
qen/pr_utils.py
qen/project.py
qen/py.typed
qen/pyproject_utils.py
qen/repo_utils.py
qen/commands/__init__.py
qen/commands/add.py
qen/commands/commit.py
qen/commands/config.py
qen/commands/delete.py
qen/commands/init.py
qen/commands/pr.py
qen/commands/pr_tui.py
qen/commands/pull.py
qen/commands/push.py
qen/commands/rm.py
qen/commands/sh.py
qen/commands/status.py
qen/commands/workspace.py
qen/context/__init__.py
qen/context/runtime.py
qen/services/__init__.py
qen/services/config_service.py
qenvy/README.md
qenvy/__init__.py
qenvy/base.py
qenvy/exceptions.py
qenvy/factory.py
qenvy/formats.py
qenvy/parameter_store.py
qenvy/protocols.py
qenvy/py.typed
qenvy/storage.py
qenvy/types.py
proj/.gitignore
proj/README.md
proj/pyproject.toml
proj/qen
qen-0.5.0.dist-info/METADATA
qen-0.5.0.dist-info/WHEEL
qen-0.5.0.dist-info/entry_points.txt
qen-0.5.0.dist-info/RECORD
