Metadata-Version: 2.4
Name: qen
Version: 0.5.0
Summary: A tiny, extensible tool for organizing multi-repository development work
Project-URL: Homepage, https://github.com/data-yaml/qen
Project-URL: Repository, https://github.com/data-yaml/qen
Project-URL: Issues, https://github.com/data-yaml/qen/issues
Author-email: Ernest Prabhakar <ernest@quilt.bio>
License: MIT
Keywords: development,git,monorepo,multi-repo,workflow
Classifier: Development Status :: 3 - Alpha
Classifier: Intended Audience :: Developers
Classifier: License :: OSI Approved :: MIT License
Classifier: Programming Language :: Python :: 3
Classifier: Programming Language :: Python :: 3.12
Classifier: Topic :: Software Development :: Version Control :: Git
Requires-Python: >=3.12
Requires-Dist: click>=8.1.0
Requires-Dist: platformdirs>=4.0.0
Requires-Dist: prompt-toolkit>=3.0.0
Requires-Dist: pyyaml>=6.0
Requires-Dist: tomli-w>=1.0.0
Requires-Dist: tomli>=2.0.0; python_version < '3.11'
Provides-Extra: aws
Requires-Dist: boto3>=1.34.0; extra == 'aws'
Provides-Extra: dev
Requires-Dist: boto3-stubs[ssm]>=1.34.0; extra == 'dev'
Requires-Dist: boto3>=1.34.0; extra == 'dev'
Requires-Dist: moto[ssm]>=5.0.0; extra == 'dev'
Requires-Dist: mypy>=1.8.0; extra == 'dev'
Requires-Dist: poethepoet>=0.24.0; extra == 'dev'
Requires-Dist: pre-commit>=4.0.0; extra == 'dev'
Requires-Dist: pytest-cov>=4.0.0; extra == 'dev'
Requires-Dist: pytest-mock>=3.12.0; extra == 'dev'
Requires-Dist: pytest>=8.0.0; extra == 'dev'
Requires-Dist: requests>=2.31.0; extra == 'dev'
Requires-Dist: ruff>=0.1.0; extra == 'dev'
Requires-Dist: typing-extensions>=4.0.0; extra == 'dev'
